xplogger/__init__.py
xplogger/logbook.py
xplogger/metrics.py
xplogger/types.py
xplogger/utils.py
xplogger/experiment_manager/__init__.py
xplogger/experiment_manager/result.py
xplogger/experiment_manager/notebook/__init__.py
xplogger/experiment_manager/notebook/utils.py
xplogger/experiment_manager/record/__init__.py
xplogger/experiment_manager/record/base.py
xplogger/experiment_manager/record/mongo.py
xplogger/experiment_manager/record/omegaconf.py
xplogger/experiment_manager/record/record_list.py
xplogger/experiment_manager/result/__init__.py
xplogger/experiment_manager/result/db.py
xplogger/experiment_manager/result/result.py
xplogger/experiment_manager/result/utils.py
xplogger/experiment_manager/slurm/__init__.py
xplogger/experiment_manager/slurm/ds.py
xplogger/experiment_manager/slurm/job.py
xplogger/experiment_manager/slurm/utils.py
xplogger/experiment_manager/store/__init__.py
xplogger/experiment_manager/store/mongo.py
xplogger/experiment_manager/utils/__init__.py
xplogger/experiment_manager/utils/enum.py
xplogger/experiment_manager/viz/__init__.py
xplogger/experiment_manager/viz/bokeh.py
xplogger/experiment_manager/viz/matplotlib.py
xplogger/experiment_manager/viz/utils.py
xplogger/logger/__init__.py
xplogger/logger/base.py
xplogger/logger/filesystem.py
xplogger/logger/localdb.py
xplogger/logger/mlflow.py
xplogger/logger/mongo.py
xplogger/logger/tensorboard.py
xplogger/logger/wandb.py
xplogger/parser/__init__.py
xplogger/parser/base.py
xplogger/parser/config.py
xplogger/parser/log.py
xplogger/parser/metric.py
xplogger/parser/utils.py
xplogger/parser/experiment/__init__.py
xplogger/parser/experiment/experiment.py
xplogger/parser/experiment/parser.py
xplogger/parser/experiment/utils.py
xplogger-0.11.3.dist-info/LICENSE
xplogger-0.11.3.dist-info/METADATA
xplogger-0.11.3.dist-info/WHEEL
xplogger-0.11.3.dist-info/top_level.txt
xplogger-0.11.3.dist-info/RECORD
