Metadata-Version: 2.1
Name: xplogger
Version: 0.11.3
Summary: Logging Utility for ML Experiments
Home-page: https://github.com/shagunsodhani/xplogger
Author: Shagun Sodhani
Author-email: sshagunsodhani@gmail.com
License: UNKNOWN
Platform: UNKNOWN
Classifier: Programming Language :: Python :: 3.7
Classifier: Programming Language :: Python :: 3.8
Classifier: Programming Language :: Python :: 3.9
Classifier: Programming Language :: Python :: 3.10
Classifier: License :: OSI Approved :: MIT License
Classifier: Operating System :: OS Independent
Requires-Python: >=3.7
Requires-Dist: numpy (>=1.20.0)
Requires-Dist: pandas (>=1.0.0)
Requires-Dist: pyarrow (>=2.0.0)
Provides-Extra: all
Requires-Dist: numpy (>=1.20.0) ; extra == 'all'
Requires-Dist: pandas (>=1.0.0) ; extra == 'all'
Requires-Dist: pyarrow (>=2.0.0) ; extra == 'all'
Requires-Dist: pymongo (>=3.11.1) ; extra == 'all'
Requires-Dist: wandb (>=0.10.11) ; extra == 'all'
Requires-Dist: tensorboardX (>=2.1) ; extra == 'all'
Requires-Dist: mlflow (>=1.12.1) ; extra == 'all'
Requires-Dist: filelock (>=3.4.2) ; extra == 'all'
Provides-Extra: dev
Requires-Dist: numpy (>=1.20.0) ; extra == 'dev'
Requires-Dist: pandas (>=1.0.0) ; extra == 'dev'
Requires-Dist: pyarrow (>=2.0.0) ; extra == 'dev'
Requires-Dist: pymongo (>=3.11.1) ; extra == 'dev'
Requires-Dist: wandb (>=0.10.11) ; extra == 'dev'
Requires-Dist: tensorboardX (>=2.1) ; extra == 'dev'
Requires-Dist: mlflow (>=1.12.1) ; extra == 'dev'
Requires-Dist: filelock (>=3.4.2) ; extra == 'dev'
Requires-Dist: black (>=22.1.0) ; extra == 'dev'
Requires-Dist: flake8-annotations (>=2.7.0) ; extra == 'dev'
Requires-Dist: flake8-bandit (>=2.1.2) ; extra == 'dev'
Requires-Dist: flake8-bugbear (>=22.1.11) ; extra == 'dev'
Requires-Dist: flake8-comprehensions (>=3.8.0) ; extra == 'dev'
Requires-Dist: flake8-docstrings (>=1.5.0) ; extra == 'dev'
Requires-Dist: flake8 (>=4.0.1) ; extra == 'dev'
Requires-Dist: isort (>=5.10.1) ; extra == 'dev'
Requires-Dist: mypy (>=0.931) ; extra == 'dev'
Requires-Dist: nox (>=2022.1.7) ; extra == 'dev'
Requires-Dist: pre-commit (>=2.17.0) ; extra == 'dev'
Requires-Dist: pytest (>=7.0.0) ; extra == 'dev'
Requires-Dist: sphinx-autodoc-annotation (>=1.0-1) ; extra == 'dev'
Requires-Dist: sphinx-rtd-theme (>=1.0.0) ; extra == 'dev'
Requires-Dist: sphinx (>=4.3.0) ; extra == 'dev'
Requires-Dist: sphinxcontrib-napoleon (>=0.7) ; extra == 'dev'
Requires-Dist: twine (>=3.8.0) ; extra == 'dev'
Requires-Dist: typing-extensions (>=4.1.0) ; extra == 'dev'
